mcp_webrtc/__init__.py
mcp_webrtc/py.typed
mcp_webrtc/webrtc.py
mcp_webrtc-0.1.0.dist-info/METADATA
mcp_webrtc-0.1.0.dist-info/WHEEL
mcp_webrtc-0.1.0.dist-info/RECORD
