Metadata-Version: 2.4
Name: mcp-webrtc
Version: 0.1.0
Summary: WebRTC Transport for Model Context Protocol
Project-URL: repository, https://github.com/pilartomas/mcp-webrtc
Author-email: Tomas Pilar <thomas7pilar@gmail.com>
License-Expression: MIT
Requires-Python: >=3.11
Requires-Dist: aiortc>=1.13.0
Requires-Dist: mcp>=1.15.0
